azureml/dataprep/ThirdPartyNotice.html
azureml/dataprep/__init__.py
azureml/dataprep/api/__init__.py
azureml/dataprep/api/_aml_auth_resolver.py
azureml/dataprep/api/_aml_helper.py
azureml/dataprep/api/_archiveoption.py
azureml/dataprep/api/_azure_access_token_resolver.py
azureml/dataprep/api/_constants.py
azureml/dataprep/api/_dask_helper.py
azureml/dataprep/api/_dataframereader.py
azureml/dataprep/api/_dataset_resolver.py
azureml/dataprep/api/_datastore_helper.py
azureml/dataprep/api/_loggerfactory.py
azureml/dataprep/api/_oauthToken.py
azureml/dataprep/api/_pandas_helper.py
azureml/dataprep/api/_rslex_executor.py
azureml/dataprep/api/_spark_helper.py
azureml/dataprep/api/_telemetry.json
azureml/dataprep/api/builders.py
azureml/dataprep/api/dataflow.py
azureml/dataprep/api/dataprofile.py
azureml/dataprep/api/datasources.py
azureml/dataprep/api/engineless_builders.py
azureml/dataprep/api/engineless_dataflow.py
azureml/dataprep/api/errorhandlers.py
azureml/dataprep/api/expressions.py
azureml/dataprep/api/functions.py
azureml/dataprep/api/inspector.py
azureml/dataprep/api/parseproperties.py
azureml/dataprep/api/readers.py
azureml/dataprep/api/references.py
azureml/dataprep/api/secretmanager.py
azureml/dataprep/api/step.py
azureml/dataprep/api/typeconversions.py
azureml/dataprep/api/types.py
azureml/dataprep/api/value.py
azureml/dataprep/api/_aml_auth/__init__.py
azureml/dataprep/api/_aml_auth/_azureml_token_authentication.py
azureml/dataprep/api/_aml_auth/_utils/__init__.py
azureml/dataprep/api/_aml_auth/_utils/chained_identity.py
azureml/dataprep/api/_aml_auth/_utils/logged_lock.py
azureml/dataprep/api/_aml_auth/_utils/async_utils/__init__.py
azureml/dataprep/api/_aml_auth/_utils/async_utils/async_task.py
azureml/dataprep/api/_aml_auth/_utils/async_utils/daemon.py
azureml/dataprep/api/_aml_auth/_utils/async_utils/task_queue.py
azureml/dataprep/api/_aml_auth/_utils/async_utils/worker_pool.py
azureml/dataprep/api/_restclient/__init__.py
azureml_dataprep-5.4.1.dist-info/licenses/LICENSE.txt
azureml_dataprep-5.4.1.dist-info/METADATA
azureml_dataprep-5.4.1.dist-info/WHEEL
azureml_dataprep-5.4.1.dist-info/entry_points.txt
azureml_dataprep-5.4.1.dist-info/top_level.txt
azureml_dataprep-5.4.1.dist-info/RECORD
