Metadata-Version: 2.4
Name: azureml-dataprep
Version: 5.4.1
Summary: Azure ML Data Preparation SDK is used to load, transform,     and write data for machine learning workflows
Author: Microsoft Corporation
Author-email: dataprepms@microsoft.com
Classifier: Development Status :: 5 - Production/Stable
Classifier: Intended Audience :: Developers
Classifier: Intended Audience :: Science/Research
Classifier: License :: Other/Proprietary License
Classifier: Programming Language :: Python
Classifier: Programming Language :: Python :: 3 :: Only
Classifier: Programming Language :: Python :: 3.8
Classifier: Programming Language :: Python :: 3.9
Classifier: Programming Language :: Python :: 3.10
Classifier: Programming Language :: Python :: 3.11
Classifier: Programming Language :: Python :: 3.12
Classifier: Operating System :: MacOS
Classifier: Operating System :: Microsoft :: Windows
Classifier: Operating System :: POSIX :: Linux
Classifier: Topic :: Scientific/Engineering
Requires-Python: >=3.8
License-File: LICENSE.txt
Requires-Dist: azureml-dataprep-native<43.0.0,>=42.0.0
Requires-Dist: azureml-dataprep-rslex~=2.25.1
Requires-Dist: cloudpickle<3.0.0,>=1.1.0
Requires-Dist: azure-identity<=1.17.0,>=1.16.0
Requires-Dist: jsonschema
Requires-Dist: pyyaml<7.0.0,>=5.1.0
Provides-Extra: pandas
Requires-Dist: numpy>=1.14.0; extra == "pandas"
Requires-Dist: pandas>=0.23.4; extra == "pandas"
Requires-Dist: pyarrow>=0.17.0; extra == "pandas"
Provides-Extra: parquet
Requires-Dist: pyarrow>=0.17.0; extra == "parquet"
Provides-Extra: pyspark
Requires-Dist: pyspark==2.3.0; extra == "pyspark"
Provides-Extra: fuse
Requires-Dist: fusepy<4.0.0,>=3.0.1; extra == "fuse"
Provides-Extra: scipy
Requires-Dist: scipy>=1.1.0; extra == "scipy"
Provides-Extra: pyarrow
Requires-Dist: pyarrow>=0.17.0; extra == "pyarrow"
Dynamic: author
Dynamic: author-email
Dynamic: classifier
Dynamic: description
Dynamic: description-content-type
Dynamic: license-file
Dynamic: provides-extra
Dynamic: requires-dist
Dynamic: requires-python
Dynamic: summary
